nmap-stubs/METADATA.toml
nmap-stubs/__init__.pyi
nmap-stubs/nmap.pyi
types_nmap-0.1.6.dist-info/METADATA
types_nmap-0.1.6.dist-info/WHEEL
types_nmap-0.1.6.dist-info/top_level.txt
types_nmap-0.1.6.dist-info/RECORD
