Metadata-Version: 2.1
Name: types-nmap
Version: 0.1.6
Summary: Typing stubs for nmap
Home-page: https://github.com/python/typeshed
License: Apache-2.0 license
Platform: UNKNOWN
Classifier: License :: OSI Approved :: Apache Software License
Classifier: Typing :: Typed
